Metadata-Version: 1.0
Name: event-connectors-wrapper-test2
Version: 0.3
Summary: A package to handle event driven engines
Home-page: https://github.com/tykiblood/kafka-wrapper
Author: OMR
Author-email: ingesql1992@hotmail.com
License: MIT
Platform: UNKNOWN
